{
  "version": 3,
  "middleware": {
    "/": {
      "files": [
        "server/edge-runtime-webpack.js",
        "server/middleware.js"
      ],
      "name": "middleware",
      "page": "/",
      "matchers": [
        {
          "regexp": "^(?:\\/(_next\\/data\\/[^/]{1,}))?(?:\\/((?!_next\\/static|_next\\/image|favicon.ico|.*.(?:svg|png|jpg|jpeg|gif|webp)$).*))(.json)?[\\/#\\?]?$",
          "originalSource": "/((?!_next/static|_next/image|favicon.ico|.*.(?:svg|png|jpg|jpeg|gif|webp)$).*)"
        }
      ],
      "wasm": [],
      "assets": [],
      "env": {
        "__NEXT_BUILD_ID": "RIv6vv6hG1GQv7P6gE-Sg",
        "NEXT_SERVER_ACTIONS_ENCRYPTION_KEY": "dvp9EkMEMNH/bvCNERF+V5LKa4WiJ3VkpvcOROu/cgQ=",
        "__NEXT_PREVIEW_MODE_ID": "cacb1af1bd78293ec0080bac701b7932",
        "__NEXT_PREVIEW_MODE_ENCRYPTION_KEY": "4096b9ca0817e24cd369ebdd5cc69d1db0c3e423285913af0f10d9f60450339a",
        "__NEXT_PREVIEW_MODE_SIGNING_KEY": "dbd92d94219676150394fa321a4a863e4112898cb424d5ccd39ba3692d687fa9"
      }
    }
  },
  "functions": {},
  "sortedMiddleware": [
    "/"
  ]
}